{
  "Ads": [
    {

      "select_ads":"ADMOB",
      "select_backup_ads":"IRON",

      "main_ads_inter":"ca-app-pub-6320795547579018/4292299699",
      "main_ads_banner":"ca-app-pub-6320795547579018/7358087363",

      "backup_ads_inter":"DefaultInterstitial",
      "backup_ads_banner":"DefaultBanner",

      "initial_sdk":"INITIALIZE_SDK",
      "initial_sdk_backup":"115737f3d",

      "interval": 0,
      "hpk1": "insurance",
      "hpk2": "aparel",
      "hpk3": "sport",
      "hpk4": "car",
      "hpk5": "vps",


      "admob_native": "ca-app-pub-6320795547579018/7358087363",
      "admob_open": "ca-app-pub-6320795547579018/9161482994",

      "startappid":"204087512",
      "ironid":"115737f3d",
      "unityid":"5464646",

      "main_puzzle": "YES",
      "status_app": "0879869867896879667567576",
      "link_redirect": "https://"
    }
  ]
}
